Metadata-Version: 2.1
Name: metatype
Version: 0.1.3.0
Summary: Implementation of base dict types for metaformat versions.
Home-page: https://github.com/wefindx/metatype
Author: Mindey
Author-email: mindey@qq.com
License: MIT
Platform: UNKNOWN
Provides-Extra: test
